genTik/__init__.py
genTik/algo.py
gentik-1.0.dist-info/METADATA
gentik-1.0.dist-info/WHEEL
gentik-1.0.dist-info/top_level.txt
gentik-1.0.dist-info/RECORD
