Metadata-Version: 2.4
Name: genTik
Version: 1.0
Summary: TikTok Sign Generator
Author: Your Name
Dynamic: author
Dynamic: summary
